[{"bizName":"TBweitao","serviceDependency":[{"serviceId":"msoa.taobao.detail.showsku","version":"1.0"}]},{"bizName":"msoa.taobao.cart.open","serviceDependency":[{"serviceId":"msoa.taobao.cart.open.add","version":"1.0"}]},{"bizName":"msoa.taobao.cart.sdk","serviceDependency":[{"serviceId":"msoa.taobao.cart.sdk.add","version":"2.0"},{"serviceId":"msoa.taobao.cart.sdk.query","version":"2.0"},{"serviceId":"msoa.taobao.detail.showsku","version":"2.0"}]},{"bizName":"msoa.taobao.search","serviceDependency":[{"serviceId":"msoa.taobao.detail.showsku","version":"1.0"},{"serviceId":"msoa.taobao.detail.showsku","version":"3.0"}]},{"bizName":"video_weex","serviceDependency":[{"serviceId":"msoa.taobao.cart.sdk.add","version":"2.0"}]},{"bizName":"msoa.taobao.homepage","serviceDependency":[{"serviceId":"msoa.taobao.abtest.dobucket","version":"1.0"}]},{"bizName":"msoa.taobao.detail","serviceDependency":[{"serviceId":"msoa.taobao.favorite.addFavoriteItem","version":"1.0"},{"serviceId":"msoa.taobao.favorite.isFavoriteItem","version":"1.0"},{"serviceId":"msoa.taobao.favorite.deleteFavoriteItem","version":"1.0"},{"serviceId":"msoa.taobao.favorite.showCategoryList","version":"1.0"}]},{"bizName":"msoa.taobao.homepage","serviceDependency":[{"serviceId":"msoa.taobao.abtest.dobucket","version":"1.0"}]},{"bizName":"msoa.taobao.detail","serviceDependency":[{"serviceId":"msoa.taobao.favorite.isFavoriteItem","version":"1.0"},{"serviceId":"msoa.taobao.favorite.showCategoryList","version":"1.0"},{"serviceId":"msoa.taobao.favorite.addFavoriteItem","version":"1.0"},{"serviceId":"msoa.taobao.favorite.deleteFavoriteItem","version":"1.0"},{"serviceId":"msoa.taobao.detail.showsku","version":"1.0"},{"serviceId":"msoa.taobao.detail.showsku","version":"2.0"},{"serviceId":"msoa.taobao.detail.add2smcart","version":"1.0"},{"serviceId":"msoa.taobao.detail.pageshow","version":"1.0"}]}]